flaskx.py
p314-0.1.0.dist-info/METADATA
p314-0.1.0.dist-info/WHEEL
p314-0.1.0.dist-info/top_level.txt
p314-0.1.0.dist-info/RECORD
