Metadata-Version: 2.4
Name: p314
Version: 0.1.0
Summary: Add your description here
Requires-Python: >=3.14
Requires-Dist: flask>=3.1.0
Requires-Dist: requests>=2.32.3
